README
setup.py
bin/ve
bin/ve-clone
bin/ve-extend
bin/ve-init
vecmd/__init__.py
vecmd/commands.py
vecmd/script.py
virtualenv_commands.egg-info/PKG-INFO
virtualenv_commands.egg-info/SOURCES.txt
virtualenv_commands.egg-info/dependency_links.txt
virtualenv_commands.egg-info/requires.txt
virtualenv_commands.egg-info/top_level.txt