Metadata-Version: 1.0
Name: virtualenv-commands
Version: 0.2.3
Summary: Additional commands for virtualenv.
Home-page: http://thisismedium.com/labs/virtualenv-commands/
Author: Medium
Author-email: labs@thisismedium.com
License: BSD
Keywords: utilities commands virtualenv
Platform: UNKNOWN
Classifier: Development Status :: 3 - Alpha
Classifier: Intended Audience :: Developers
Classifier: License :: OSI Approved :: BSD License
Classifier: Operating System :: Unix
Classifier: Programming Language :: Python
Classifier: Topic :: Utilities
